{"_type":"export","__export_format":4,"__export_date":"2020-03-05T03:42:39.400Z","__export_source":"insomnia.desktop.app:v7.1.1","resources":[{"_id":"req_66246a150fff442f866a5e3f573950ff","authentication":{},"body":{},"created":1572140390715,"description":"","headers":[],"isPrivate":false,"metaSortKey":-1572140390715,"method":"GET","modified":1572140470754,"name":"teste","parameters":[],"parentId":"wrk_b5a46974959744f4b42af052d1826915","settingDisableRenderRequestBody":false,"settingEncodeUrl":true,"settingFollowRedirects":"global","settingRebuildPath":true,"settingSendCookies":true,"settingStoreCookies":true,"url":"http://api.acordeon.mus.br:3333/","_type":"request"},{"_id":"wrk_b5a46974959744f4b42af052d1826915","created":1571512035446,"description":"","modified":1571512035446,"name":"Insomnia","parentId":null,"_type":"workspace"},{"_id":"req_9a9f4a3db7aa430c82a031eeb4df5d46","authentication":{},"body":{},"created":1572418703204,"description":"","headers":[],"isPrivate":false,"metaSortKey":-1572616897072,"method":"GET","modified":1573818720857,"name":"INDEX","parameters":[],"parentId":"wrk_08b43477c6db4af082f49c7862c41415","settingDisableRenderRequestBody":false,"settingEncodeUrl":true,"settingFollowRedirects":"global","settingRebuildPath":true,"settingSendCookies":true,"settingStoreCookies":true,"url":"http://api.acordeon.mus.br:3333/","_type":"request"},{"_id":"wrk_08b43477c6db4af082f49c7862c41415","created":1572418652474,"description":"","modified":1572418652474,"name":"Api Acordeon","parentId":null,"_type":"workspace"},{"_id":"req_bf7b8e6c35254383b986ffe58845a221","authentication":{},"body":{},"created":1583255138670,"description":"","headers":[],"isPrivate":false,"metaSortKey":-1583258102202,"method":"GET","modified":1583258451246,"name":"Index","parameters":[],"parentId":"wrk_143fe6bb95d54ed6a82be26e1b978b69","settingDisableRenderRequestBody":false,"settingEncodeUrl":true,"settingFollowRedirects":"global","settingRebuildPath":true,"settingSendCookies":true,"settingStoreCookies":true,"url":"http://devJob/api/admin/users","_type":"request"},{"_id":"wrk_143fe6bb95d54ed6a82be26e1b978b69","created":1583255128862,"description":"","modified":1583255128862,"name":"DevJobs","parentId":null,"_type":"workspace"},{"_id":"req_762a3ac7c19c48e695d90da0447ef60e","authentication":{},"body":{},"created":1571526320820,"description":"","headers":[],"isPrivate":false,"metaSortKey":-1571526343752,"method":"GET","modified":1571529126001,"name":"Lista Usuarios","parameters":[],"parentId":"fld_b9de744932d34f0d8eb4cf671768b46f","settingDisableRenderRequestBody":false,"settingEncodeUrl":true,"settingFollowRedirects":"global","settingRebuildPath":true,"settingSendCookies":true,"settingStoreCookies":true,"url":"http://api.acordeon.mus.br:3000/users/","_type":"request"},{"_id":"fld_b9de744932d34f0d8eb4cf671768b46f","created":1571526343802,"description":"","environment":{},"environmentPropertyOrder":null,"metaSortKey":-1571526343802,"modified":1571526343802,"name":"InitApiNode","parentId":"wrk_b5a46974959744f4b42af052d1826915","_type":"request_group"},{"_id":"req_1b9ffeac99744700b687e0726e136141","authentication":{},"body":{},"created":1571528743394,"description":"","headers":[],"isPrivate":false,"metaSortKey":-1571526343702,"method":"GET","modified":1572140370645,"name":"Busca Usuario ","parameters":[],"parentId":"fld_b9de744932d34f0d8eb4cf671768b46f","settingDisableRenderRequestBody":false,"settingEncodeUrl":true,"settingFollowRedirects":"global","settingRebuildPath":true,"settingSendCookies":true,"settingStoreCookies":true,"url":"http://api.acordeon.mus.br:3000/users/1","_type":"request"},{"_id":"req_79ded30b6557402ab6dd653afe527ed6","authentication":{},"body":{"mimeType":"application/json","text":"{\n\t\"user\": \"Lidio\"\n}"},"created":1571528898054,"description":"","headers":[{"id":"pair_c8ecfa85ca434bd3b25aa0940ff3ae30","name":"Content-Type","value":"application/json"}],"isPrivate":false,"metaSortKey":-1571526343652,"method":"POST","modified":1571534165519,"name":"Cria Usuario","parameters":[],"parentId":"fld_b9de744932d34f0d8eb4cf671768b46f","settingDisableRenderRequestBody":false,"settingEncodeUrl":true,"settingFollowRedirects":"global","settingRebuildPath":true,"settingSendCookies":true,"settingStoreCookies":true,"url":"http://api.acordeon.mus.br:3000/users","_type":"request"},{"_id":"req_9943bb0de76b44759e0355646c261b50","authentication":{},"body":{"mimeType":"application/json","text":"{\n\t\"user\": \"João Maria\"\n}"},"created":1571529460479,"description":"","headers":[{"id":"pair_c8ecfa85ca434bd3b25aa0940ff3ae30","name":"Content-Type","value":"application/json"}],"isPrivate":false,"metaSortKey":-1571526343602,"method":"PUT","modified":1571535122560,"name":"Edita Usuario","parameters":[],"parentId":"fld_b9de744932d34f0d8eb4cf671768b46f","settingDisableRenderRequestBody":false,"settingEncodeUrl":true,"settingFollowRedirects":"global","settingRebuildPath":true,"settingSendCookies":true,"settingStoreCookies":true,"url":"http://api.acordeon.mus.br:3000/users/2","_type":"request"},{"_id":"req_bd03da6c6caf445880985b9c61d4ec24","authentication":{},"body":{},"created":1571529735712,"description":"","headers":[],"isPrivate":false,"metaSortKey":-1571526343552,"method":"DELETE","modified":1571530560638,"name":"Delata Usuario","parameters":[],"parentId":"fld_b9de744932d34f0d8eb4cf671768b46f","settingDisableRenderRequestBody":false,"settingEncodeUrl":true,"settingFollowRedirects":"global","settingRebuildPath":true,"settingSendCookies":true,"settingStoreCookies":true,"url":"http://api.acordeon.mus.br:3000/users/2","_type":"request"},{"_id":"req_154efb6291ab45bf878e1a91c5dd40a0","authentication":{},"body":{"mimeType":"application/json","text":"{\n\t\"username\": \"jfhenrique\",\n\t\"email\": \"jhsg.dev@gmail.com\",\n\t\"password\": \"123456\",\n\t\"password_confirmation\": \"123456\",\n\t\"nickname\": \"Jefferson\",\n\t\"goTo\": \"\",\n\t\"friend\": {\n    \"key\": \"1d21b7b8-8f89-413f-b861-bbe85c06ae9b\"\n  }\n}\n"},"created":1572637114228,"description":"","headers":[{"id":"pair_4ca56be3b8f54d65bc2f7daa84275375","name":"Content-Type","value":"application/json"},{"id":"pair_1030e27732da42e091b52a471dd52095","name":"Accept","value":"application/json"}],"isPrivate":false,"metaSortKey":-1572279546959.5,"method":"POST","modified":1577477164004,"name":"REGISTRO","parameters":[],"parentId":"fld_2a422d428ba04f92bdcf1bd6f7d59a46","settingDisableRenderRequestBody":false,"settingEncodeUrl":true,"settingFollowRedirects":"global","settingRebuildPath":true,"settingSendCookies":true,"settingStoreCookies":true,"url":"{{ app_url }}/auth/signup","_type":"request"},{"_id":"fld_2a422d428ba04f92bdcf1bd6f7d59a46","created":1572418683461,"description":"","environment":{},"environmentPropertyOrder":null,"metaSortKey":-1572616897047,"modified":1574461808301,"name":"Auth","parentId":"wrk_08b43477c6db4af082f49c7862c41415","_type":"request_group"},{"_id":"req_f4f4a0758b084ced9f778f8deb0f9e51","authentication":{},"body":{"mimeType":"application/json","text":"{\n\t\"username\": \"jfhenrique\",\n\t\"email\": \"jhsg.dev@gmail.com\",\n\t\"password\": \"123456\"\n}"},"created":1572729671519,"description":"","headers":[{"id":"pair_4ca56be3b8f54d65bc2f7daa84275375","name":"Content-Type","value":"application/json"},{"id":"pair_a8ab8a27fa6e4585a3239ffafb72f09a","name":"Accept","value":"application/json"}],"isPrivate":false,"metaSortKey":-1572175179776.125,"method":"POST","modified":1579699027795,"name":"AUTENTICACAO","parameters":[],"parentId":"fld_2a422d428ba04f92bdcf1bd6f7d59a46","settingDisableRenderRequestBody":false,"settingEncodeUrl":true,"settingFollowRedirects":"global","settingRebuildPath":true,"settingSendCookies":true,"settingStoreCookies":true,"url":"{{ app_url  }}/auth/signin","_type":"request"},{"_id":"req_2b8060e20bc4464a8a4df7b283785d39","authentication":{},"body":{},"created":1573819003641,"description":"","headers":[{"id":"pair_11023557894c4cb6946218503b468697","name":"Accept","value":"application/json"}],"isPrivate":false,"metaSortKey":-1572227363367.8125,"method":"GET","modified":1579687023107,"name":"CONFIRMAÇÃO","parameters":[],"parentId":"fld_2a422d428ba04f92bdcf1bd6f7d59a46","settingDisableRenderRequestBody":false,"settingEncodeUrl":true,"settingFollowRedirects":"global","settingRebuildPath":true,"settingSendCookies":true,"settingStoreCookies":true,"url":"{{ app_url }}/auth/signup/confirm/ZnzQOy2f6C1BmePcNwJ53gR2VrhEyPiV","_type":"request"},{"_id":"req_e6cac2a8d21046d2ac691cdbbd616070","authentication":{},"body":{"mimeType":"application/json","text":"{\n\t\"username\": \"jfhenrique\",\n\t\"email\": \"jhsg.dev@gmail.com\"\n}"},"created":1573827598063,"description":"","headers":[{"id":"pair_4ca56be3b8f54d65bc2f7daa84275375","name":"Content-Type","value":"application/json"},{"id":"pair_a8ab8a27fa6e4585a3239ffafb72f09a","name":"Accept","value":"application/json"}],"isPrivate":false,"metaSortKey":-1572175179751.125,"method":"POST","modified":1575622571270,"name":"ESQUECI SENHA","parameters":[],"parentId":"fld_2a422d428ba04f92bdcf1bd6f7d59a46","settingDisableRenderRequestBody":false,"settingEncodeUrl":true,"settingFollowRedirects":"global","settingRebuildPath":true,"settingSendCookies":true,"settingStoreCookies":true,"url":"{{ app_url  }}/auth/forgot/password","_type":"request"},{"_id":"req_6015302236f74ba7b4a8354cc931de05","authentication":{},"body":{},"created":1573998466321,"description":"","headers":[{"id":"pair_11023557894c4cb6946218503b468697","name":"Accept","value":"application/json"}],"isPrivate":false,"metaSortKey":-1572175179701.125,"method":"GET","modified":1575622577768,"name":"RECUPERAR SENHA","parameters":[],"parentId":"fld_2a422d428ba04f92bdcf1bd6f7d59a46","settingDisableRenderRequestBody":false,"settingEncodeUrl":true,"settingFollowRedirects":"global","settingRebuildPath":true,"settingSendCookies":true,"settingStoreCookies":true,"url":"{{ app_url  }}/auth/forgot/password/2d7c33a9dcf3970c46db1a0723a60663","_type":"request"},{"_id":"req_6bd37e8df54044f7b87af2a1a4bf6b3c","authentication":{},"body":{"mimeType":"application/json","text":"{\n\t\"token\": \"2d7c33a9dcf3970c46db1a0723a60663\",\n\t\"username\": \"jfhenrique\",\n\t\"email\": \"jhsg.dev@gmail.com\",\n\t\"password\": \"jh123\",\n\t\"password_confirmation\": \"jh123\"\n}"},"created":1574000677926,"description":"","headers":[{"id":"pair_4ca56be3b8f54d65bc2f7daa84275375","name":"Content-Type","value":"application/json"},{"id":"pair_a8ab8a27fa6e4585a3239ffafb72f09a","name":"Accept","value":"application/json"}],"isPrivate":false,"metaSortKey":-1572175179651.125,"method":"PUT","modified":1575929965548,"name":"ALTERAR SENHA","parameters":[],"parentId":"fld_2a422d428ba04f92bdcf1bd6f7d59a46","settingDisableRenderRequestBody":false,"settingEncodeUrl":true,"settingFollowRedirects":"global","settingRebuildPath":true,"settingSendCookies":true,"settingStoreCookies":true,"url":"{{ app_url  }}/auth/change/password","_type":"request"},{"_id":"req_9c2ce81b0b1a4880a86041d564d31288","authentication":{"token":"{{ token  }}","type":"bearer"},"body":{"mimeType":"application/json","text":"{\n\t\"refresh_token\": \"{{ refreshToken  }}\"\n}"},"created":1574084640103,"description":"","headers":[{"id":"pair_4ca56be3b8f54d65bc2f7daa84275375","name":"Content-Type","value":"application/json"},{"id":"pair_a8ab8a27fa6e4585a3239ffafb72f09a","name":"Accept","value":"application/json"}],"isPrivate":false,"metaSortKey":-1572175179763.625,"method":"POST","modified":1575561659969,"name":"SAIR","parameters":[],"parentId":"fld_2a422d428ba04f92bdcf1bd6f7d59a46","settingDisableRenderRequestBody":false,"settingEncodeUrl":true,"settingFollowRedirects":"global","settingRebuildPath":true,"settingSendCookies":true,"settingStoreCookies":true,"url":"{{ app_url  }}/auth/logout","_type":"request"},{"_id":"req_f791be089a8c468d98d13a4e7a228a53","authentication":{},"body":{"mimeType":"application/json","text":"{\n\t\"refresh_token\": \"{{ refreshToken  }}\"\n}"},"created":1574265333308,"description":"","headers":[{"id":"pair_4ca56be3b8f54d65bc2f7daa84275375","name":"Content-Type","value":"application/json"},{"id":"pair_a8ab8a27fa6e4585a3239ffafb72f09a","name":"Accept","value":"application/json"}],"isPrivate":false,"metaSortKey":-1572175179757.375,"method":"POST","modified":1574463421022,"name":"ATUALIZA TOKEN","parameters":[],"parentId":"fld_2a422d428ba04f92bdcf1bd6f7d59a46","settingDisableRenderRequestBody":false,"settingEncodeUrl":true,"settingFollowRedirects":"global","settingRebuildPath":true,"settingSendCookies":true,"settingStoreCookies":true,"url":"{{ app_url  }}/auth/refresh","_type":"request"},{"_id":"req_6f3695fbf88c4e16ac794fdd3966dfe3","authentication":{},"body":{"mimeType":"application/json","text":"{\n\t\"username\": \"jfhenrique\",\n\t\"email\": \"jhsg.dev@gmail.com\",\n\t\"password\": \"123456\"\n}"},"created":1579586322058,"description":"","headers":[{"id":"pair_f4cf2e2f34a24bf9ad53e5dd7743aa86","name":"Content-Type","value":"application/json"}],"isPrivate":false,"metaSortKey":-1579586322058,"method":"POST","modified":1579586905520,"name":"signIn","parameters":[],"parentId":"fld_113c612012d94e10ba91dd8d7a0f3b8e","settingDisableRenderRequestBody":false,"settingEncodeUrl":true,"settingFollowRedirects":"global","settingRebuildPath":true,"settingSendCookies":true,"settingStoreCookies":true,"url":"{{ app_url  }}/auth/signin","_type":"request"},{"_id":"fld_113c612012d94e10ba91dd8d7a0f3b8e","created":1579586237354,"description":"","environment":{},"environmentPropertyOrder":null,"metaSortKey":-1579586237354,"modified":1579586237354,"name":"Auth","parentId":"wrk_25ad120a03044a1d90d4a21232852391","_type":"request_group"},{"_id":"wrk_25ad120a03044a1d90d4a21232852391","created":1579586198729,"description":"","modified":1579586198729,"name":"SeperCorretor","parentId":null,"_type":"workspace"},{"_id":"req_da126a1a92174e9ea55b34e070a71ca5","authentication":{},"body":{"mimeType":"application/json","text":"{\n\t\"username\": \"devJobs\",\n\t\"password\": \"123456\"\n}"},"created":1583258119056,"description":"","headers":[{"id":"pair_803fae67929440f385d276d1eec44075","name":"Content-Type","value":"application/json"},{"description":"","id":"pair_f9d223bd7e314b3dba2b73488bfb056f","name":"Accept","value":"application/json"}],"isPrivate":false,"metaSortKey":-1583258119056,"method":"POST","modified":1583353946891,"name":"login","parameters":[],"parentId":"fld_99bf8524597b4ebf9cbcc40a76cdf78c","settingDisableRenderRequestBody":false,"settingEncodeUrl":true,"settingFollowRedirects":"global","settingRebuildPath":true,"settingSendCookies":true,"settingStoreCookies":true,"url":"{{ app_url  }}/auth/login","_type":"request"},{"_id":"fld_99bf8524597b4ebf9cbcc40a76cdf78c","created":1583258102152,"description":"","environment":{},"environmentPropertyOrder":null,"metaSortKey":-1583258102152,"modified":1583258102152,"name":"Auth","parentId":"wrk_143fe6bb95d54ed6a82be26e1b978b69","_type":"request_group"},{"_id":"req_49494c80afa44ffe96ca6fa495a0a5d9","authentication":{"disabled":false,"token":"{{ token  }}","type":"bearer"},"body":{"mimeType":"application/json","text":""},"created":1583341210501,"description":"","headers":[{"id":"pair_803fae67929440f385d276d1eec44075","name":"Content-Type","value":"application/json"},{"description":"","id":"pair_f9d223bd7e314b3dba2b73488bfb056f","name":"Accept","value":"application/json"}],"isPrivate":false,"metaSortKey":-1583258110629,"method":"POST","modified":1583344727179,"name":"logout","parameters":[],"parentId":"fld_99bf8524597b4ebf9cbcc40a76cdf78c","settingDisableRenderRequestBody":false,"settingEncodeUrl":true,"settingFollowRedirects":"global","settingRebuildPath":true,"settingSendCookies":true,"settingStoreCookies":true,"url":"{{ app_url  }}/auth/logout","_type":"request"},{"_id":"req_ca2363ec72414f87b7cef0ab3c03f8fe","authentication":{"disabled":false,"token":"{{ token  }}","type":"bearer"},"body":{},"created":1583343612999,"description":"","headers":[],"isPrivate":false,"metaSortKey":-1583343612999,"method":"GET","modified":1583351341851,"name":"me","parameters":[],"parentId":"fld_99bf8524597b4ebf9cbcc40a76cdf78c","settingDisableRenderRequestBody":false,"settingEncodeUrl":true,"settingFollowRedirects":"global","settingRebuildPath":true,"settingSendCookies":true,"settingStoreCookies":true,"url":"{{ app_url  }}/auth/me","_type":"request"},{"_id":"req_eb41554a1eb44ee7acf771861cf36b64","authentication":{"disabled":false,"token":"{{ token  }}","type":"bearer"},"body":{"mimeType":"application/json","text":""},"created":1583344697943,"description":"","headers":[{"id":"pair_803fae67929440f385d276d1eec44075","name":"Content-Type","value":"application/json"},{"description":"","id":"pair_f9d223bd7e314b3dba2b73488bfb056f","name":"Accept","value":"application/json"}],"isPrivate":false,"metaSortKey":-1583258106415.5,"method":"POST","modified":1583344719554,"name":"refresh","parameters":[],"parentId":"fld_99bf8524597b4ebf9cbcc40a76cdf78c","settingDisableRenderRequestBody":false,"settingEncodeUrl":true,"settingFollowRedirects":"global","settingRebuildPath":true,"settingSendCookies":true,"settingStoreCookies":true,"url":"{{ app_url  }}/auth/refresh","_type":"request"},{"_id":"req_53ee26cd1d204268bfac858edc638479","authentication":{"disabled":false,"token":"{{ token  }}","type":"bearer"},"body":{},"created":1572616914894,"description":"","headers":[{"id":"pair_c8c3e6eaf782426eb842ca2b3a5ac373","name":"Accept","value":"application/json"}],"isPrivate":false,"metaSortKey":-1572616914894,"method":"GET","modified":1575592580024,"name":"List","parameters":[],"parentId":"fld_3bf15b708e71460d91392eb350e22b9a","settingDisableRenderRequestBody":false,"settingEncodeUrl":true,"settingFollowRedirects":"global","settingRebuildPath":true,"settingSendCookies":true,"settingStoreCookies":true,"url":"{{ app_url  }}/admin/products","_type":"request"},{"_id":"fld_3bf15b708e71460d91392eb350e22b9a","created":1572616897022,"description":"","environment":{},"environmentPropertyOrder":null,"metaSortKey":-1572967435795.3125,"modified":1578179564866,"name":"products","parentId":"fld_6167eec400134938a4108cdb15377c7d","_type":"request_group"},{"_id":"fld_6167eec400134938a4108cdb15377c7d","created":1574462503574,"description":"","environment":{},"environmentPropertyOrder":null,"metaSortKey":-1572616897034.5,"modified":1574462510314,"name":"Admin","parentId":"wrk_08b43477c6db4af082f49c7862c41415","_type":"request_group"},{"_id":"req_e5d5a24fa7dd4d05beac81e3cc7eda4f","authentication":{"disabled":false,"token":"{{ token  }}","type":"bearer"},"body":{"mimeType":"application/json","text":"{\n\t\"name\": \"Aula\",\n\t\"description\": \"cadastra uma aula\",\n\t\"credit\": 1,\n\t\"price\": \"50.00\",\n\t\"score\": 1,\n\t\"bonus\":[\n\t\t{\n\t\t\t\"qtd\": 5,\n\t\t\t\"pontos\": 5\n\t\t},\n\t\t{\n\t\t\t\"qtd\": 10,\n\t\t\t\"pontos\": 10\n\t\t}\n\t]\n}"},"created":1572616948719,"description":"","headers":[{"id":"pair_fb6e6ba7ccb3417ba41e21f6999736df","name":"Content-Type","value":"application/json"},{"id":"pair_3e4a304dad0b4a6e9888f2429f6b421f","name":"Accept","value":"application/json"}],"isPrivate":false,"metaSortKey":-1572517809049,"method":"POST","modified":1579692993937,"name":"Create","parameters":[],"parentId":"fld_3bf15b708e71460d91392eb350e22b9a","settingDisableRenderRequestBody":false,"settingEncodeUrl":true,"settingFollowRedirects":"global","settingRebuildPath":true,"settingSendCookies":true,"settingStoreCookies":true,"url":"{{ app_url  }}/admin/products","_type":"request"},{"_id":"req_1bb5b349db18440cb0fa130ca85ae50d","authentication":{"disabled":false,"token":"{{ token  }}","type":"bearer"},"body":{},"created":1575561756995,"description":"","headers":[{"id":"pair_c8c3e6eaf782426eb842ca2b3a5ac373","name":"Accept","value":"application/json"}],"isPrivate":false,"metaSortKey":-1572567361971.5,"method":"GET","modified":1575592561140,"name":"Get","parameters":[],"parentId":"fld_3bf15b708e71460d91392eb350e22b9a","settingDisableRenderRequestBody":false,"settingEncodeUrl":true,"settingFollowRedirects":"global","settingRebuildPath":true,"settingSendCookies":true,"settingStoreCookies":true,"url":"{{ app_url  }}/admin/products/1","_type":"request"},{"_id":"req_7f192f3071554a669c8a12bf8e86b064","authentication":{"disabled":false,"token":"{{ token  }}","type":"bearer"},"body":{"mimeType":"application/json","text":"{\n\t\"name\": \"Credito Inicial\"\n}"},"created":1575561763879,"description":"","headers":[{"id":"pair_fb6e6ba7ccb3417ba41e21f6999736df","name":"Content-Type","value":"application/json"},{"id":"pair_3e4a304dad0b4a6e9888f2429f6b421f","name":"Accept","value":"application/json"}],"isPrivate":false,"metaSortKey":-1572517808999,"method":"PUT","modified":1575623218764,"name":"Update","parameters":[],"parentId":"fld_3bf15b708e71460d91392eb350e22b9a","settingDisableRenderRequestBody":false,"settingEncodeUrl":true,"settingFollowRedirects":"global","settingRebuildPath":true,"settingSendCookies":true,"settingStoreCookies":true,"url":"{{ app_url  }}/admin/products/1","_type":"request"},{"_id":"req_be888c5285c94cf6a02c47c86d545a20","authentication":{"disabled":false,"token":"{{ token  }}","type":"bearer"},"body":{},"created":1575561775693,"description":"","headers":[{"id":"pair_c8c3e6eaf782426eb842ca2b3a5ac373","name":"Accept","value":"application/json"}],"isPrivate":false,"metaSortKey":-1572517808949,"method":"DELETE","modified":1575592661097,"name":"Delete","parameters":[],"parentId":"fld_3bf15b708e71460d91392eb350e22b9a","settingDisableRenderRequestBody":false,"settingEncodeUrl":true,"settingFollowRedirects":"global","settingRebuildPath":true,"settingSendCookies":true,"settingStoreCookies":true,"url":"{{ app_url  }}/admin/products/1","_type":"request"},{"_id":"req_23adbb8c23ed416b85448d20da792a1a","authentication":{"disabled":false,"token":"{{ token  }}","type":"bearer"},"body":{},"created":1574513410746,"description":"","headers":[{"id":"pair_c8c3e6eaf782426eb842ca2b3a5ac373","name":"Accept","value":"application/json"}],"isPrivate":false,"metaSortKey":-1572616905983,"method":"GET","modified":1577303592866,"name":"Index","parameters":[{"description":"","id":"pair_4cd102a3ffff4652bd234037c6fd1071","name":"page","value":"1"},{"description":"","disabled":false,"id":"pair_0485601736ae49e3a5826561d6ee13e6","name":"limit","value":"5"},{"description":"","disabled":true,"id":"pair_b3c5dfd63dd348b88e41c4e4c5a96723","name":"name","value":"Cadastrar"}],"parentId":"fld_fd21b08787fc4f4b81b5b032c935f72f","settingDisableRenderRequestBody":false,"settingEncodeUrl":true,"settingFollowRedirects":"global","settingRebuildPath":true,"settingSendCookies":true,"settingStoreCookies":true,"url":"{{ app_url  }}/admin/permissions","_type":"request"},{"_id":"fld_fd21b08787fc4f4b81b5b032c935f72f","created":1574486437038,"description":"","environment":{},"environmentPropertyOrder":null,"metaSortKey":-1574486437038,"modified":1574486437038,"name":"permissions","parentId":"fld_6167eec400134938a4108cdb15377c7d","_type":"request_group"},{"_id":"req_c959389044ce4740ae55f7b2d704b0f4","authentication":{"disabled":false,"token":"{{ token  }}","type":"bearer"},"body":{"mimeType":"application/json","text":"{\n\t\"name\": \"Cadastrar Produtos\",\n\t\"slug\": \"cadastra_produto\",\n\t\"description\": \"Cadastrar um novo produto\"\n}"},"created":1574513414787,"description":"","headers":[{"id":"pair_fb6e6ba7ccb3417ba41e21f6999736df","name":"Content-Type","value":"application/json"},{"id":"pair_3e4a304dad0b4a6e9888f2429f6b421f","name":"Accept","value":"application/json"}],"isPrivate":false,"metaSortKey":-1572616901477.5,"method":"POST","modified":1575622897778,"name":"Create","parameters":[],"parentId":"fld_fd21b08787fc4f4b81b5b032c935f72f","settingDisableRenderRequestBody":false,"settingEncodeUrl":true,"settingFollowRedirects":"global","settingRebuildPath":true,"settingSendCookies":true,"settingStoreCookies":true,"url":"{{ app_url  }}/admin/permissions","_type":"request"},{"_id":"req_85aed65fc29a42409ed464550ffe330f","authentication":{"disabled":false,"token":"{{ token  }}","type":"bearer"},"body":{},"created":1574513486288,"description":"","headers":[{"id":"pair_c8c3e6eaf782426eb842ca2b3a5ac373","name":"Accept","value":"application/json"}],"isPrivate":false,"metaSortKey":-1572616903730.25,"method":"GET","modified":1575622837037,"name":"Get","parameters":[],"parentId":"fld_fd21b08787fc4f4b81b5b032c935f72f","settingDisableRenderRequestBody":false,"settingEncodeUrl":true,"settingFollowRedirects":"global","settingRebuildPath":true,"settingSendCookies":true,"settingStoreCookies":true,"url":"{{ app_url  }}/admin/permissions/1","_type":"request"},{"_id":"req_10281f39daee4dea92a4c681e00ae9dd","authentication":{"disabled":false,"token":"{{ token  }}","type":"bearer"},"body":{"mimeType":"application/json","text":"{\n\t\"name\": \"Cadastrar Produto\"\n}"},"created":1574513967061,"description":"","headers":[{"id":"pair_fb6e6ba7ccb3417ba41e21f6999736df","name":"Content-Type","value":"application/json"},{"id":"pair_3e4a304dad0b4a6e9888f2429f6b421f","name":"Accept","value":"application/json"}],"isPrivate":false,"metaSortKey":-1572616899274.75,"method":"PUT","modified":1575622976209,"name":"Update","parameters":[],"parentId":"fld_fd21b08787fc4f4b81b5b032c935f72f","settingDisableRenderRequestBody":false,"settingEncodeUrl":true,"settingFollowRedirects":"global","settingRebuildPath":true,"settingSendCookies":true,"settingStoreCookies":true,"url":"{{ app_url  }}/admin/permissions/1","_type":"request"},{"_id":"req_8dae87a8febc4275aebf57aea83705e7","authentication":{"disabled":false,"token":"{{ token  }}","type":"bearer"},"body":{},"created":1574514025984,"description":"","headers":[{"id":"pair_c8c3e6eaf782426eb842ca2b3a5ac373","name":"Accept","value":"application/json"}],"isPrivate":false,"metaSortKey":-1572616899224.75,"method":"DELETE","modified":1574514043763,"name":"Delete","parameters":[],"parentId":"fld_fd21b08787fc4f4b81b5b032c935f72f","settingDisableRenderRequestBody":false,"settingEncodeUrl":true,"settingFollowRedirects":"global","settingRebuildPath":true,"settingSendCookies":true,"settingStoreCookies":true,"url":"{{ app_url  }}/admin/permissions/1","_type":"request"},{"_id":"req_d1723f72d5f74e36a1262c044f1ef660","authentication":{"disabled":false,"token":"{{ token  }}","type":"bearer"},"body":{},"created":1574517954822,"description":"","headers":[{"id":"pair_c8c3e6eaf782426eb842ca2b3a5ac373","name":"Accept","value":"application/json"}],"isPrivate":false,"metaSortKey":-1572616905983,"method":"GET","modified":1574521287243,"name":"Index","parameters":[],"parentId":"fld_bd28139ed5f04673881934bec436a7dd","settingDisableRenderRequestBody":false,"settingEncodeUrl":true,"settingFollowRedirects":"global","settingRebuildPath":true,"settingSendCookies":true,"settingStoreCookies":true,"url":"{{ app_url  }}/admin/roles","_type":"request"},{"_id":"fld_bd28139ed5f04673881934bec436a7dd","created":1574517954814,"description":"","environment":{},"environmentPropertyOrder":null,"metaSortKey":-1573551667042.5,"modified":1574517968923,"name":"roles","parentId":"fld_6167eec400134938a4108cdb15377c7d","_type":"request_group"},{"_id":"req_df71f41868584ec5a1744dd80ccc33f0","authentication":{"disabled":false,"token":"{{ token  }}","type":"bearer"},"body":{"mimeType":"application/json","text":"{\n\t\"name\": \"Adminis\",\n\t\"slug\": \"admin\",\n\t\"description\": \"Administra o sistema\",\n\t\"permissions\": [1]\n}"},"created":1574517954828,"description":"","headers":[{"id":"pair_fb6e6ba7ccb3417ba41e21f6999736df","name":"Content-Type","value":"application/json"},{"id":"pair_3e4a304dad0b4a6e9888f2429f6b421f","name":"Accept","value":"application/json"}],"isPrivate":false,"metaSortKey":-1572616901477.5,"method":"POST","modified":1575623051211,"name":"Create","parameters":[],"parentId":"fld_bd28139ed5f04673881934bec436a7dd","settingDisableRenderRequestBody":false,"settingEncodeUrl":true,"settingFollowRedirects":"global","settingRebuildPath":true,"settingSendCookies":true,"settingStoreCookies":true,"url":"{{ app_url  }}/admin/roles","_type":"request"},{"_id":"req_01383c36f56343669545f75c7544fed3","authentication":{"disabled":false,"token":"{{ token  }}","type":"bearer"},"body":{},"created":1574517954835,"description":"","headers":[{"id":"pair_c8c3e6eaf782426eb842ca2b3a5ac373","name":"Accept","value":"application/json"}],"isPrivate":false,"metaSortKey":-1572616901527.5,"method":"GET","modified":1575623030461,"name":"Get","parameters":[],"parentId":"fld_bd28139ed5f04673881934bec436a7dd","settingDisableRenderRequestBody":false,"settingEncodeUrl":true,"settingFollowRedirects":"global","settingRebuildPath":true,"settingSendCookies":true,"settingStoreCookies":true,"url":"{{ app_url  }}/admin/roles/1","_type":"request"},{"_id":"req_1c54e4648ff745168b664b4e44badada","authentication":{"disabled":false,"token":"{{ token  }}","type":"bearer"},"body":{"mimeType":"application/json","text":"{\n\t\"name\": \"Administrador\"\n}"},"created":1574517954842,"description":"","headers":[{"id":"pair_fb6e6ba7ccb3417ba41e21f6999736df","name":"Content-Type","value":"application/json"},{"id":"pair_3e4a304dad0b4a6e9888f2429f6b421f","name":"Accept","value":"application/json"}],"isPrivate":false,"metaSortKey":-1572616899274.75,"method":"PUT","modified":1575623072234,"name":"Update","parameters":[],"parentId":"fld_bd28139ed5f04673881934bec436a7dd","settingDisableRenderRequestBody":false,"settingEncodeUrl":true,"settingFollowRedirects":"global","settingRebuildPath":true,"settingSendCookies":true,"settingStoreCookies":true,"url":"{{ app_url  }}/admin/roles/1","_type":"request"},{"_id":"req_1228cb7450104f6face25a00d706ac5b","authentication":{"disabled":false,"token":"{{ token  }}","type":"bearer"},"body":{},"created":1574517954847,"description":"","headers":[{"id":"pair_c8c3e6eaf782426eb842ca2b3a5ac373","name":"Accept","value":"application/json"}],"isPrivate":false,"metaSortKey":-1572616899224.75,"method":"DELETE","modified":1575761651735,"name":"Delete","parameters":[],"parentId":"fld_bd28139ed5f04673881934bec436a7dd","settingDisableRenderRequestBody":false,"settingEncodeUrl":true,"settingFollowRedirects":"global","settingRebuildPath":true,"settingSendCookies":true,"settingStoreCookies":true,"url":"{{ app_url  }}/admin/roles/1","_type":"request"},{"_id":"req_849a62fddcfe4c569efe414581317634","authentication":{"disabled":false,"token":"{{ token  }}","type":"bearer"},"body":{},"created":1575595263981,"description":"","headers":[{"id":"pair_c8c3e6eaf782426eb842ca2b3a5ac373","name":"Accept","value":"application/json"}],"isPrivate":false,"metaSortKey":-1572616914894,"method":"GET","modified":1575624324363,"name":"List","parameters":[],"parentId":"fld_19b3ea9ffb734959a92553d49d6e3d0d","settingDisableRenderRequestBody":false,"settingEncodeUrl":true,"settingFollowRedirects":"global","settingRebuildPath":true,"settingSendCookies":true,"settingStoreCookies":true,"url":"{{ app_url  }}/admin/configscore","_type":"request"},{"_id":"fld_19b3ea9ffb734959a92553d49d6e3d0d","created":1575595263973,"description":"","environment":{},"environmentPropertyOrder":null,"metaSortKey":-1573025858920.0312,"modified":1578179576115,"name":"scoreconfig","parentId":"fld_6167eec400134938a4108cdb15377c7d","_type":"request_group"},{"_id":"req_5fbc52edc5214532ae1ff2ec4db1babf","authentication":{"disabled":false,"token":"{{ token  }}","type":"bearer"},"body":{"mimeType":"application/json","text":"{\n\t\"name\": \"music\",\n\t\"description\": \"pontos para registro de musica\",\n\t\"quantity\": 1\n}"},"created":1575595263985,"description":"","headers":[{"id":"pair_fb6e6ba7ccb3417ba41e21f6999736df","name":"Content-Type","value":"application/json"},{"id":"pair_3e4a304dad0b4a6e9888f2429f6b421f","name":"Accept","value":"application/json"}],"isPrivate":false,"metaSortKey":-1572517809049,"method":"POST","modified":1575930471015,"name":"Create","parameters":[],"parentId":"fld_19b3ea9ffb734959a92553d49d6e3d0d","settingDisableRenderRequestBody":false,"settingEncodeUrl":true,"settingFollowRedirects":"global","settingRebuildPath":true,"settingSendCookies":true,"settingStoreCookies":true,"url":"{{ app_url  }}/admin/configscore","_type":"request"},{"_id":"req_d6864cb7bd3c4e4f837af131b29adc26","authentication":{"disabled":false,"token":"{{ token  }}","type":"bearer"},"body":{},"created":1575595263990,"description":"","headers":[{"id":"pair_c8c3e6eaf782426eb842ca2b3a5ac373","name":"Accept","value":"application/json"}],"isPrivate":false,"metaSortKey":-1572567361971.5,"method":"GET","modified":1575930137527,"name":"Get","parameters":[],"parentId":"fld_19b3ea9ffb734959a92553d49d6e3d0d","settingDisableRenderRequestBody":false,"settingEncodeUrl":true,"settingFollowRedirects":"global","settingRebuildPath":true,"settingSendCookies":true,"settingStoreCookies":true,"url":"{{ app_url  }}/admin/configscore/1","_type":"request"},{"_id":"req_c54a752aff494967a47fb8f53b5aa95b","authentication":{"disabled":false,"token":"{{ token  }}","type":"bearer"},"body":{"mimeType":"application/json","text":"{\n\t\"description\": \"pontos para registro de musica teste\"\n}"},"created":1575595263994,"description":"","headers":[{"id":"pair_fb6e6ba7ccb3417ba41e21f6999736df","name":"Content-Type","value":"application/json"},{"id":"pair_3e4a304dad0b4a6e9888f2429f6b421f","name":"Accept","value":"application/json"}],"isPrivate":false,"metaSortKey":-1572517808999,"method":"PUT","modified":1575930531273,"name":"Update","parameters":[],"parentId":"fld_19b3ea9ffb734959a92553d49d6e3d0d","settingDisableRenderRequestBody":false,"settingEncodeUrl":true,"settingFollowRedirects":"global","settingRebuildPath":true,"settingSendCookies":true,"settingStoreCookies":true,"url":"{{ app_url  }}/admin/configscore/1","_type":"request"},{"_id":"req_13102ca560aa494aa05b8c9081195b72","authentication":{"disabled":false,"token":"{{ token  }}","type":"bearer"},"body":{},"created":1575595263998,"description":"","headers":[{"id":"pair_c8c3e6eaf782426eb842ca2b3a5ac373","name":"Accept","value":"application/json"}],"isPrivate":false,"metaSortKey":-1572517808949,"method":"DELETE","modified":1575930591332,"name":"Delete","parameters":[],"parentId":"fld_19b3ea9ffb734959a92553d49d6e3d0d","settingDisableRenderRequestBody":false,"settingEncodeUrl":true,"settingFollowRedirects":"global","settingRebuildPath":true,"settingSendCookies":true,"settingStoreCookies":true,"url":"{{ app_url  }}/admin/configscore/1","_type":"request"},{"_id":"req_5185627767484028bb8d3e116c9be355","authentication":{"disabled":false,"token":"{{ token  }}","type":"bearer"},"body":{},"created":1575665304666,"description":"","headers":[{"id":"pair_c8c3e6eaf782426eb842ca2b3a5ac373","name":"Accept","value":"application/json"}],"isPrivate":false,"metaSortKey":-1572616905983,"method":"GET","modified":1577299367556,"name":"Index","parameters":[],"parentId":"fld_c39702cfcab347ac866221983200eaa3","settingDisableRenderRequestBody":false,"settingEncodeUrl":true,"settingFollowRedirects":"global","settingRebuildPath":true,"settingSendCookies":true,"settingStoreCookies":true,"url":"{{ app_url  }}/admin/users","_type":"request"},{"_id":"fld_c39702cfcab347ac866221983200eaa3","created":1575665304651,"description":"","environment":{},"environmentPropertyOrder":null,"metaSortKey":-1573084282044.75,"modified":1575665352673,"name":"users","parentId":"fld_6167eec400134938a4108cdb15377c7d","_type":"request_group"},{"_id":"req_ac9547f53664490893c06a2ae6659870","authentication":{"disabled":false,"token":"{{ token  }}","type":"bearer"},"body":{"mimeType":"application/json","text":"{\n\t\"username\": \"weltonq\",\n\t\"email\": \"weltonq.dev@gmail.com\",\n\t\"password\": \"123456\",\n\t\"password_confirmation\": \"123456\",\n\t\"is_active\": true,\n\t\"nickname\": \"Welton\",\n\t\"roles\": [2]\n}\n"},"created":1575665304672,"description":"","headers":[{"id":"pair_fb6e6ba7ccb3417ba41e21f6999736df","name":"Content-Type","value":"application/json"},{"id":"pair_3e4a304dad0b4a6e9888f2429f6b421f","name":"Accept","value":"application/json"}],"isPrivate":false,"metaSortKey":-1572616901477.5,"method":"POST","modified":1575780701323,"name":"Create","parameters":[],"parentId":"fld_c39702cfcab347ac866221983200eaa3","settingDisableRenderRequestBody":false,"settingEncodeUrl":true,"settingFollowRedirects":"global","settingRebuildPath":true,"settingSendCookies":true,"settingStoreCookies":true,"url":"{{ app_url  }}/admin/users","_type":"request"},{"_id":"req_c904e499c9a44b75a4bbb1de5e9b7f94","authentication":{"disabled":false,"token":"{{ token  }}","type":"bearer"},"body":{},"created":1575665304675,"description":"","headers":[{"id":"pair_c8c3e6eaf782426eb842ca2b3a5ac373","name":"Accept","value":"application/json"}],"isPrivate":false,"metaSortKey":-1572616901527.5,"method":"GET","modified":1575763096320,"name":"Get","parameters":[],"parentId":"fld_c39702cfcab347ac866221983200eaa3","settingDisableRenderRequestBody":false,"settingEncodeUrl":true,"settingFollowRedirects":"global","settingRebuildPath":true,"settingSendCookies":true,"settingStoreCookies":true,"url":"{{ app_url  }}/admin/users/1d4c76ab-51e9-4651-9b64-a6f2e0eac092","_type":"request"},{"_id":"req_d8c5b3e064d0432fadc51f97d8b2a771","authentication":{"disabled":false,"token":"{{ token  }}","type":"bearer"},"body":{"mimeType":"application/json","text":"{\n\t\"username\": \"welton\",\t\n\t\"roles\": [2,3]\n}"},"created":1575665304678,"description":"","headers":[{"id":"pair_fb6e6ba7ccb3417ba41e21f6999736df","name":"Content-Type","value":"application/json"},{"id":"pair_3e4a304dad0b4a6e9888f2429f6b421f","name":"Accept","value":"application/json"}],"isPrivate":false,"metaSortKey":-1572616899274.75,"method":"PUT","modified":1575781487177,"name":"Update","parameters":[],"parentId":"fld_c39702cfcab347ac866221983200eaa3","settingDisableRenderRequestBody":false,"settingEncodeUrl":true,"settingFollowRedirects":"global","settingRebuildPath":true,"settingSendCookies":true,"settingStoreCookies":true,"url":"{{ app_url  }}/admin/users/0edea7ce-6c89-4c35-9d81-b0df1f5eacc1","_type":"request"},{"_id":"req_53d652897b084e129bcdecc2c03e0937","authentication":{"disabled":false,"token":"{{ token  }}","type":"bearer"},"body":{},"created":1575665304680,"description":"","headers":[{"id":"pair_c8c3e6eaf782426eb842ca2b3a5ac373","name":"Accept","value":"application/json"}],"isPrivate":false,"metaSortKey":-1572616899224.75,"method":"DELETE","modified":1577301932945,"name":"Delete","parameters":[],"parentId":"fld_c39702cfcab347ac866221983200eaa3","settingDisableRenderRequestBody":false,"settingEncodeUrl":true,"settingFollowRedirects":"global","settingRebuildPath":true,"settingSendCookies":true,"settingStoreCookies":true,"url":"{{ app_url  }}/admin/users/3955c0d7-a123-4dbb-8ede-0844c854cba0","_type":"request"},{"_id":"req_94f4f54d759b4f768d67f0f2202ea71c","authentication":{"disabled":false,"token":"{{ token  }}","type":"bearer"},"body":{},"created":1577363703370,"description":"","headers":[{"id":"pair_c8c3e6eaf782426eb842ca2b3a5ac373","name":"Accept","value":"application/json"}],"isPrivate":false,"metaSortKey":-1572616905983,"method":"GET","modified":1577750276804,"name":"Index","parameters":[],"parentId":"fld_fec329ec1e7840d18e70ac5f0291ad90","settingDisableRenderRequestBody":false,"settingEncodeUrl":true,"settingFollowRedirects":"global","settingRebuildPath":true,"settingSendCookies":true,"settingStoreCookies":true,"url":"{{ app_url  }}/admin/orders","_type":"request"},{"_id":"fld_fec329ec1e7840d18e70ac5f0291ad90","created":1577363703356,"description":"","environment":{},"environmentPropertyOrder":null,"metaSortKey":-1572850589545.875,"modified":1577363703356,"name":"orders","parentId":"fld_6167eec400134938a4108cdb15377c7d","_type":"request_group"},{"_id":"req_51b779d911014cd19d1fbe4f019f0a28","authentication":{"disabled":false,"token":"{{ token  }}","type":"bearer"},"body":{"mimeType":"application/json","text":"{\n\t\"user_key\": \"f2273dd6-562b-41f7-8420-e598ca05e15d\",\n\t\"items\": [\n\t\t{\n\t\t\t\"product_id\": 2,\n\t\t\t\"quantity\": 1\n\t\t},\n\t\t{\n\t\t\t\"product_id\": 1,\n\t\t\t\"quantity\": 1\n\t\t}\n\t],\n\t\"status\": 1\n}\n"},"created":1577363703376,"description":"","headers":[{"id":"pair_fb6e6ba7ccb3417ba41e21f6999736df","name":"Content-Type","value":"application/json"},{"id":"pair_3e4a304dad0b4a6e9888f2429f6b421f","name":"Accept","value":"application/json"}],"isPrivate":false,"metaSortKey":-1572616901477.5,"method":"POST","modified":1579692885090,"name":"Create","parameters":[],"parentId":"fld_fec329ec1e7840d18e70ac5f0291ad90","settingDisableRenderRequestBody":false,"settingEncodeUrl":true,"settingFollowRedirects":"global","settingRebuildPath":true,"settingSendCookies":true,"settingStoreCookies":true,"url":"{{ app_url  }}/admin/orders","_type":"request"},{"_id":"req_0f3725c2d4f946609b074d2e261875d7","authentication":{"disabled":false,"token":"{{ token  }}","type":"bearer"},"body":{},"created":1577363703379,"description":"","headers":[{"id":"pair_c8c3e6eaf782426eb842ca2b3a5ac373","name":"Accept","value":"application/json"}],"isPrivate":false,"metaSortKey":-1572616901527.5,"method":"GET","modified":1577653905538,"name":"Get","parameters":[],"parentId":"fld_fec329ec1e7840d18e70ac5f0291ad90","settingDisableRenderRequestBody":false,"settingEncodeUrl":true,"settingFollowRedirects":"global","settingRebuildPath":true,"settingSendCookies":true,"settingStoreCookies":true,"url":"{{ app_url  }}/admin/orders/c9d18029-b51f-4df7-ba3c-d81ee148d5ef","_type":"request"},{"_id":"req_ab95099fb51f40c49768b150fff18ae7","authentication":{"disabled":false,"token":"{{ token  }}","type":"bearer"},"body":{"mimeType":"application/json","text":"{\n\t\"user_key\": \"bd32fafd-d067-47f9-b894-be3eb6df1445\",\n\t\"items\": [\n\t\t{\n\t\t\t\"id\": 3,\n\t\t\t\"product_id\": 1,\n\t\t\t\"quantity\": 2\n\t\t},\n\t\t{\n\t\t\t\"id\": 4,\n\t\t\t\"product_id\": 1,\n\t\t\t\"quantity\": 2\n\t\t},\n\t\t{\n\t\t\t\"product_id\": 2,\n\t\t\t\"quantity\": 1\n\t\t}\n\t],\n\t\"status\": 2\n}"},"created":1577363703381,"description":"","headers":[{"id":"pair_fb6e6ba7ccb3417ba41e21f6999736df","name":"Content-Type","value":"application/json"},{"id":"pair_3e4a304dad0b4a6e9888f2429f6b421f","name":"Accept","value":"application/json"}],"isPrivate":false,"metaSortKey":-1572616899274.75,"method":"PUT","modified":1577653750148,"name":"Update","parameters":[],"parentId":"fld_fec329ec1e7840d18e70ac5f0291ad90","settingDisableRenderRequestBody":false,"settingEncodeUrl":true,"settingFollowRedirects":"global","settingRebuildPath":true,"settingSendCookies":true,"settingStoreCookies":true,"url":"{{ app_url  }}/admin/orders/c9d18029-b51f-4df7-ba3c-d81ee148d5ef","_type":"request"},{"_id":"req_3dcf2f3eeef8453ab8abfef056fe508b","authentication":{"disabled":false,"token":"{{ token  }}","type":"bearer"},"body":{},"created":1577363703383,"description":"","headers":[{"id":"pair_c8c3e6eaf782426eb842ca2b3a5ac373","name":"Accept","value":"application/json"}],"isPrivate":false,"metaSortKey":-1572616899224.75,"method":"DELETE","modified":1577653807268,"name":"Delete","parameters":[],"parentId":"fld_fec329ec1e7840d18e70ac5f0291ad90","settingDisableRenderRequestBody":false,"settingEncodeUrl":true,"settingFollowRedirects":"global","settingRebuildPath":true,"settingSendCookies":true,"settingStoreCookies":true,"url":"{{ app_url  }}/admin/orders/c9d18029-b51f-4df7-ba3c-d81ee148d5ef","_type":"request"},{"_id":"req_c1764173254149a79a030635817cd7e3","authentication":{"disabled":false,"token":"{{ token  }}","type":"bearer"},"body":{},"created":1577750154777,"description":"","headers":[{"id":"pair_c8c3e6eaf782426eb842ca2b3a5ac373","name":"Accept","value":"application/json"}],"isPrivate":false,"metaSortKey":-1572616914894,"method":"GET","modified":1577750297396,"name":"List","parameters":[],"parentId":"fld_03ad87eb66c649709f269c9c29ca30ec","settingDisableRenderRequestBody":false,"settingEncodeUrl":true,"settingFollowRedirects":"global","settingRebuildPath":true,"settingSendCookies":true,"settingStoreCookies":true,"url":"{{ app_url  }}/admin/paymentMethods","_type":"request"},{"_id":"fld_03ad87eb66c649709f269c9c29ca30ec","created":1577750154768,"description":"","environment":{},"environmentPropertyOrder":null,"metaSortKey":-1572909012670.5938,"modified":1578179570611,"name":"paymentMethod","parentId":"fld_6167eec400134938a4108cdb15377c7d","_type":"request_group"},{"_id":"req_0378158216d64a328e8155a999478be6","authentication":{"disabled":false,"token":"{{ token  }}","type":"bearer"},"body":{"mimeType":"application/json","text":"{\n\t\"name\": \"Boleto\",\n\t\"slug\": \"BOLETO\"\n}"},"created":1577750154783,"description":"","headers":[{"id":"pair_fb6e6ba7ccb3417ba41e21f6999736df","name":"Content-Type","value":"application/json"},{"id":"pair_3e4a304dad0b4a6e9888f2429f6b421f","name":"Accept","value":"application/json"}],"isPrivate":false,"metaSortKey":-1572517809049,"method":"POST","modified":1579693054912,"name":"Create","parameters":[],"parentId":"fld_03ad87eb66c649709f269c9c29ca30ec","settingDisableRenderRequestBody":false,"settingEncodeUrl":true,"settingFollowRedirects":"global","settingRebuildPath":true,"settingSendCookies":true,"settingStoreCookies":true,"url":"{{ app_url  }}/admin/paymentMethods","_type":"request"},{"_id":"req_99652eb18d2f4f288f2598bdc03a75c9","authentication":{"disabled":false,"token":"{{ token  }}","type":"bearer"},"body":{},"created":1577750154790,"description":"","headers":[{"id":"pair_c8c3e6eaf782426eb842ca2b3a5ac373","name":"Accept","value":"application/json"}],"isPrivate":false,"metaSortKey":-1572567361971.5,"method":"GET","modified":1577750301994,"name":"Get","parameters":[],"parentId":"fld_03ad87eb66c649709f269c9c29ca30ec","settingDisableRenderRequestBody":false,"settingEncodeUrl":true,"settingFollowRedirects":"global","settingRebuildPath":true,"settingSendCookies":true,"settingStoreCookies":true,"url":"{{ app_url  }}/admin/paymentMethods/1","_type":"request"},{"_id":"req_26d24dbe78114b3aa4bc8a1c7160545f","authentication":{"disabled":false,"token":"{{ token  }}","type":"bearer"},"body":{"mimeType":"application/json","text":"{\n\t\"name\": \"Cartão de Crédito\",\n\t\"slug\": \"CARTAO\"\n}"},"created":1577750154796,"description":"","headers":[{"id":"pair_fb6e6ba7ccb3417ba41e21f6999736df","name":"Content-Type","value":"application/json"},{"id":"pair_3e4a304dad0b4a6e9888f2429f6b421f","name":"Accept","value":"application/json"}],"isPrivate":false,"metaSortKey":-1572517808999,"method":"PUT","modified":1577751294081,"name":"Update","parameters":[],"parentId":"fld_03ad87eb66c649709f269c9c29ca30ec","settingDisableRenderRequestBody":false,"settingEncodeUrl":true,"settingFollowRedirects":"global","settingRebuildPath":true,"settingSendCookies":true,"settingStoreCookies":true,"url":"{{ app_url  }}/admin/paymentMethods/1","_type":"request"},{"_id":"req_7914a0fa4dff4735b1d3a9ab605c2675","authentication":{"disabled":false,"token":"{{ token  }}","type":"bearer"},"body":{},"created":1577750154799,"description":"","headers":[{"id":"pair_c8c3e6eaf782426eb842ca2b3a5ac373","name":"Accept","value":"application/json"}],"isPrivate":false,"metaSortKey":-1572517808949,"method":"DELETE","modified":1577750434934,"name":"Delete","parameters":[],"parentId":"fld_03ad87eb66c649709f269c9c29ca30ec","settingDisableRenderRequestBody":false,"settingEncodeUrl":true,"settingFollowRedirects":"global","settingRebuildPath":true,"settingSendCookies":true,"settingStoreCookies":true,"url":"{{ app_url  }}/admin/paymentMethods/1","_type":"request"},{"_id":"req_6e67f7cb427a4d3eb76364d882d6e289","authentication":{"disabled":false,"token":"{{ token  }}","type":"bearer"},"body":{},"created":1578179618538,"description":"","headers":[{"id":"pair_c8c3e6eaf782426eb842ca2b3a5ac373","name":"Accept","value":"application/json"}],"isPrivate":false,"metaSortKey":-1572616905983,"method":"GET","modified":1578179632572,"name":"Index","parameters":[],"parentId":"fld_0233538b0f594032a3c8460735e23e5b","settingDisableRenderRequestBody":false,"settingEncodeUrl":true,"settingFollowRedirects":"global","settingRebuildPath":true,"settingSendCookies":true,"settingStoreCookies":true,"url":"{{ app_url  }}/admin/payment","_type":"request"},{"_id":"fld_0233538b0f594032a3c8460735e23e5b","created":1578179618526,"description":"","environment":{},"environmentPropertyOrder":null,"metaSortKey":-1572733743296.4375,"modified":1578179618526,"name":"payment","parentId":"fld_6167eec400134938a4108cdb15377c7d","_type":"request_group"},{"_id":"req_e04829f0a9cd488fa9b5a68819a07096","authentication":{"disabled":false,"token":"{{ token  }}","type":"bearer"},"body":{"mimeType":"application/json","text":"{\n\t\"user_key\": \"bd32fafd-d067-47f9-b894-be3eb6df1445\",\n\t\"items\": [\n\t\t{\n\t\t\t\"product_id\": 1,\n\t\t\t\"quantity\": 1\n\t\t},\n\t\t{\n\t\t\t\"product_id\": 1,\n\t\t\t\"quantity\": 3\n\t\t}\n\t],\n\t\"status\": 1\n}\n"},"created":1578179618545,"description":"","headers":[{"id":"pair_fb6e6ba7ccb3417ba41e21f6999736df","name":"Content-Type","value":"application/json"},{"id":"pair_3e4a304dad0b4a6e9888f2429f6b421f","name":"Accept","value":"application/json"}],"isPrivate":false,"metaSortKey":-1572616901477.5,"method":"POST","modified":1578179618545,"name":"Create","parameters":[],"parentId":"fld_0233538b0f594032a3c8460735e23e5b","settingDisableRenderRequestBody":false,"settingEncodeUrl":true,"settingFollowRedirects":"global","settingRebuildPath":true,"settingSendCookies":true,"settingStoreCookies":true,"url":"{{ app_url  }}/admin/orders","_type":"request"},{"_id":"req_cb7a2d1cea314f75813890aca072a4e3","authentication":{"disabled":false,"token":"{{ token  }}","type":"bearer"},"body":{},"created":1578179618550,"description":"","headers":[{"id":"pair_c8c3e6eaf782426eb842ca2b3a5ac373","name":"Accept","value":"application/json"}],"isPrivate":false,"metaSortKey":-1572616901527.5,"method":"GET","modified":1578179618550,"name":"Get","parameters":[],"parentId":"fld_0233538b0f594032a3c8460735e23e5b","settingDisableRenderRequestBody":false,"settingEncodeUrl":true,"settingFollowRedirects":"global","settingRebuildPath":true,"settingSendCookies":true,"settingStoreCookies":true,"url":"{{ app_url  }}/admin/orders/c9d18029-b51f-4df7-ba3c-d81ee148d5ef","_type":"request"},{"_id":"req_5569855de6af48dfaef35db833c7674e","authentication":{"disabled":false,"token":"{{ token  }}","type":"bearer"},"body":{"mimeType":"application/json","text":"{\n\t\"user_key\": \"bd32fafd-d067-47f9-b894-be3eb6df1445\",\n\t\"items\": [\n\t\t{\n\t\t\t\"id\": 3,\n\t\t\t\"product_id\": 1,\n\t\t\t\"quantity\": 2\n\t\t},\n\t\t{\n\t\t\t\"id\": 4,\n\t\t\t\"product_id\": 1,\n\t\t\t\"quantity\": 2\n\t\t},\n\t\t{\n\t\t\t\"product_id\": 2,\n\t\t\t\"quantity\": 1\n\t\t}\n\t],\n\t\"status\": 2\n}"},"created":1578179618554,"description":"","headers":[{"id":"pair_fb6e6ba7ccb3417ba41e21f6999736df","name":"Content-Type","value":"application/json"},{"id":"pair_3e4a304dad0b4a6e9888f2429f6b421f","name":"Accept","value":"application/json"}],"isPrivate":false,"metaSortKey":-1572616899274.75,"method":"PUT","modified":1578179618554,"name":"Update","parameters":[],"parentId":"fld_0233538b0f594032a3c8460735e23e5b","settingDisableRenderRequestBody":false,"settingEncodeUrl":true,"settingFollowRedirects":"global","settingRebuildPath":true,"settingSendCookies":true,"settingStoreCookies":true,"url":"{{ app_url  }}/admin/orders/c9d18029-b51f-4df7-ba3c-d81ee148d5ef","_type":"request"},{"_id":"req_c0928bcad0e9473ebff9a766939c539b","authentication":{"disabled":false,"token":"{{ token  }}","type":"bearer"},"body":{},"created":1578179618559,"description":"","headers":[{"id":"pair_c8c3e6eaf782426eb842ca2b3a5ac373","name":"Accept","value":"application/json"}],"isPrivate":false,"metaSortKey":-1572616899224.75,"method":"DELETE","modified":1578179618559,"name":"Delete","parameters":[],"parentId":"fld_0233538b0f594032a3c8460735e23e5b","settingDisableRenderRequestBody":false,"settingEncodeUrl":true,"settingFollowRedirects":"global","settingRebuildPath":true,"settingSendCookies":true,"settingStoreCookies":true,"url":"{{ app_url  }}/admin/orders/c9d18029-b51f-4df7-ba3c-d81ee148d5ef","_type":"request"},{"_id":"req_11700f121d094926bf541d5ee90274e5","authentication":{},"body":{"mimeType":"application/json","text":"{\n\t\"user_id\": 1,\n\t\"fullname\": \"Jefferson Henrique Sousa Galvão\",\n\t\"cpf\": \"095.447.084-21\",\n\t\"rg\": \"002434234\",\n\t\"gender\": \"M\",\n\t\"birthday\": \"12/01/1995\",\n\t\"addresses\": [\n\t\t{\n\t\t\t\"zip\": \"59010-070\",\n\t\t\t\"street\": \"Rua Feliciano Dias\",\n\t\t\t\"number\": \"138A\",\n\t\t\t\"complement\": \"\",\n\t\t\t\"district\": \"Praia do Meio\",\n\t\t\t\"city\": \"Natal\",\n\t\t\t\"state\": \"Rio Grande do Norte\",\n\t\t\t\"country\": \"Brasil\"\t\t\t\t\n\t\t}\n\t],\n\t\"contacts\":[\n\t\t{\n\t\t\t\"name\": \"Jefferson\",\n\t\t\t\"type\": \"Pessoal\",\n\t\t\t\"number\": \"(84) 99680-6958\"\t\t\t\n\t\t}\t\n\t]\n}"},"created":1574537863762,"description":"","headers":[{"id":"pair_6144475d991a4ae7bc9367536d314a25","name":"Content-Type","value":"application/json"},{"id":"pair_d0b3d62209c543f88f53cf4348222515","name":"Accept","value":"application/json"}],"isPrivate":false,"metaSortKey":-1574537984348,"method":"PUT","modified":1574903815955,"name":"COMPLETAR REGISTRO","parameters":[],"parentId":"fld_a7e992af92f54402bbc3f84a5b6f687e","settingDisableRenderRequestBody":false,"settingEncodeUrl":true,"settingFollowRedirects":"global","settingRebuildPath":true,"settingSendCookies":true,"settingStoreCookies":true,"url":"{{ app_url  }}/register","_type":"request"},{"_id":"fld_a7e992af92f54402bbc3f84a5b6f687e","created":1574538104934,"description":"","environment":{},"environmentPropertyOrder":null,"metaSortKey":-1574538104934,"modified":1574538104934,"name":"Registro","parentId":"fld_bfd6c8196c104333b40c9f320a460f4a","_type":"request_group"},{"_id":"fld_bfd6c8196c104333b40c9f320a460f4a","created":1574537778296,"description":"","environment":{},"environmentPropertyOrder":null,"metaSortKey":-1572616896984.5,"modified":1574537787300,"name":"Client","parentId":"wrk_08b43477c6db4af082f49c7862c41415","_type":"request_group"},{"_id":"req_7dc6628cff6f457396b230e404bd32db","authentication":{"token":"{{ token  }}","type":"bearer"},"body":{"mimeType":"application/json","text":"{\t\n\t\"holder\": false,\n\t\"customer\": {\n\t\t\"name\": \"Jefferson Henrique\",\n\t\t\"email\": \"jhsg.dev@gmail.com\",\n\t\t\"cpf\": \"09544708421\",\n\t\t\"rg\": \"002434234\",\n\t\t\"phone\": \"+5584996806958\",\n\t\t\"ip\": \"179.156.54.169\"\n\t},\n\t\"address\": {\n\t\t\"state\": \"RN\",\n\t\t\"city\": \"Natal\",\n\t\t\"neighborhood\": \"Praia do Meio\",\n\t\t\"street\": \"Rua Feliciano Dias\",\n\t\t\"street_number\": \"138\",\n\t\t\"zipcode\": \"59010070\"\t\t\n\t},\t\t\n\t\"payment_method_id\": 2,\n\t\"installments\": 2,\n\t\"save_card\": false,\n\t\"card_id\": \"card_ck5128g9c08bav06ewl04n4s5\",\n\t\"card_hash\": \"{{ card_hash  }}\"\t\n}"},"created":1576206426878,"description":"","headers":[{"id":"pair_4bdd3a443fc847d4979e678de0ad1bb7","name":"Content-Type","value":"application/json"}],"isPrivate":false,"metaSortKey":-1576206426878,"method":"POST","modified":1579698813039,"name":"create","parameters":[],"parentId":"fld_056a5c6b845b4aec955a2cea87bc9ed8","settingDisableRenderRequestBody":false,"settingEncodeUrl":true,"settingFollowRedirects":"global","settingRebuildPath":true,"settingSendCookies":true,"settingStoreCookies":true,"url":"{{ app_url  }}/payments/orders/4bc1d107-8f30-4d7f-a256-20627d7fbb5a","_type":"request"},{"_id":"fld_056a5c6b845b4aec955a2cea87bc9ed8","created":1576206411318,"description":"","environment":{},"environmentPropertyOrder":null,"metaSortKey":-1576206411318,"modified":1576206411318,"name":"Pagamento","parentId":"fld_bfd6c8196c104333b40c9f320a460f4a","_type":"request_group"},{"_id":"req_6e01e1bb7f19406fb2295b1dc995a95c","authentication":{"disabled":false,"token":"{{ token  }}","type":"bearer"},"body":{},"created":1582634513608,"description":"","headers":[{"id":"pair_c8c3e6eaf782426eb842ca2b3a5ac373","name":"Accept","value":"application/json"}],"isPrivate":false,"metaSortKey":-1572616901527.5,"method":"GET","modified":1582638908289,"name":"Get","parameters":[],"parentId":"fld_56f7adc1983344ddb3e25f7f481406e8","settingDisableRenderRequestBody":false,"settingEncodeUrl":true,"settingFollowRedirects":"global","settingRebuildPath":true,"settingSendCookies":true,"settingStoreCookies":true,"url":"{{ app_url  }}/profile","_type":"request"},{"_id":"fld_56f7adc1983344ddb3e25f7f481406e8","created":1582634513576,"description":"","environment":{},"environmentPropertyOrder":null,"metaSortKey":-1576206411368,"modified":1582638567225,"name":"profile","parentId":"fld_bfd6c8196c104333b40c9f320a460f4a","_type":"request_group"},{"_id":"req_e9923329fca848a49999a4ab60380023","authentication":{"disabled":false,"token":"{{ token  }}","type":"bearer"},"body":{"mimeType":"application/json","text":"{\n\t\"username\": \"admin.acordeon\",\n\t\"email\": \"acordeon.mus@gmail.com\",\n\t\"nickname\": \"App Acordeon\"\n}"},"created":1582634513616,"description":"","headers":[{"id":"pair_fb6e6ba7ccb3417ba41e21f6999736df","name":"Content-Type","value":"application/json"},{"id":"pair_3e4a304dad0b4a6e9888f2429f6b421f","name":"Accept","value":"application/json"}],"isPrivate":false,"metaSortKey":-1572616899274.75,"method":"PUT","modified":1582638917556,"name":"Update","parameters":[],"parentId":"fld_56f7adc1983344ddb3e25f7f481406e8","settingDisableRenderRequestBody":false,"settingEncodeUrl":true,"settingFollowRedirects":"global","settingRebuildPath":true,"settingSendCookies":true,"settingStoreCookies":true,"url":"{{ app_url  }}/profile ","_type":"request"},{"_id":"req_2d23887d3f0146d69ddee3b466e15f0b","authentication":{"disabled":false,"token":"{{ token  }}","type":"bearer"},"body":{"mimeType":"multipart/form-data","params":[{"description":"","fileName":"C:\\Users\\usuario\\Pictures\\jefferson.jpg","id":"pair_0624255a485a48a899d62ce50bfc203f","name":"avatar","type":"file","value":""}]},"created":1582639054172,"description":"","headers":[{"id":"pair_fb6e6ba7ccb3417ba41e21f6999736df","name":"Content-Type","value":"multipart/form-data"},{"id":"pair_3e4a304dad0b4a6e9888f2429f6b421f","name":"Accept","value":"application/json"}],"isPrivate":false,"metaSortKey":-1572616899249.75,"method":"POST","modified":1582781713213,"name":"Upload Avatar","parameters":[],"parentId":"fld_56f7adc1983344ddb3e25f7f481406e8","settingDisableRenderRequestBody":false,"settingEncodeUrl":true,"settingFollowRedirects":"global","settingRebuildPath":true,"settingSendCookies":true,"settingStoreCookies":true,"url":"{{ app_url  }}/profile/avatar","_type":"request"},{"_id":"req_88b23bcd34524023875bdf135730d9ae","authentication":{"disabled":false,"token":"{{ token  }}","type":"bearer"},"body":{},"created":1582646503131,"description":"","headers":[{"id":"pair_c8c3e6eaf782426eb842ca2b3a5ac373","name":"Accept","value":"application/json"}],"isPrivate":false,"metaSortKey":-1572616899262.25,"method":"GET","modified":1582646511631,"name":"Get Avatar","parameters":[],"parentId":"fld_56f7adc1983344ddb3e25f7f481406e8","settingDisableRenderRequestBody":false,"settingEncodeUrl":true,"settingFollowRedirects":"global","settingRebuildPath":true,"settingSendCookies":true,"settingStoreCookies":true,"url":"{{ app_url  }}/profile/avatar","_type":"request"},{"_id":"req_e73e8b5f9c05407e81fce7c69bdc5e15","authentication":{"disabled":false,"token":"{{ token  }}","type":"bearer"},"body":{},"created":1582780311682,"description":"","headers":[{"id":"pair_c8c3e6eaf782426eb842ca2b3a5ac373","name":"Accept","value":"application/json"}],"isPrivate":false,"metaSortKey":-1572616899199.75,"method":"DELETE","modified":1582780447588,"name":"Delete","parameters":[],"parentId":"fld_56f7adc1983344ddb3e25f7f481406e8","settingDisableRenderRequestBody":false,"settingEncodeUrl":true,"settingFollowRedirects":"global","settingRebuildPath":true,"settingSendCookies":true,"settingStoreCookies":true,"url":"{{ app_url  }}/profile/avatar","_type":"request"},{"_id":"req_a7f706f4e25e463596585c7814c3dff4","authentication":{"disabled":false,"token":"{{ token  }}","type":"bearer"},"body":{},"created":1583257867615,"description":"","headers":[{"description":"","disabled":false,"id":"pair_4b043b7dd8ba4b04933eb16c81732805","name":"Accept","value":"application/json"}],"isPrivate":false,"metaSortKey":-1583258064471,"method":"GET","modified":1583353921304,"name":"all","parameters":[],"parentId":"fld_7fc51db2559e468297d5ec8b9093e434","settingDisableRenderRequestBody":false,"settingEncodeUrl":true,"settingFollowRedirects":"global","settingRebuildPath":true,"settingSendCookies":true,"settingStoreCookies":true,"url":"http://devJob/api/admin/users","_type":"request"},{"_id":"fld_7fc51db2559e468297d5ec8b9093e434","created":1583258064521,"description":"","environment":{},"environmentPropertyOrder":null,"metaSortKey":-1583258064521,"modified":1583258064521,"name":"Users","parentId":"fld_a7c872fe59d74b19af93161d88dad449","_type":"request_group"},{"_id":"fld_a7c872fe59d74b19af93161d88dad449","created":1583257808323,"description":"","environment":{},"environmentPropertyOrder":null,"metaSortKey":-1583257808324,"modified":1583257808323,"name":"Admin","parentId":"wrk_143fe6bb95d54ed6a82be26e1b978b69","_type":"request_group"},{"_id":"req_4c87340006c64f8aa3a9ea461baceead","authentication":{"token":"{{ token  }}","type":"bearer"},"body":{"mimeType":"application/json","text":"{\n\t\"name\": \"user\",\n\t\"email\": \"jhsg1.dev@gmail.com\",\n\t\"username\": \"teste\",\n\t\"password\": \"12345678\",\n\t\"password_confirmation\": \"12345678\",\n\t\"contacts\": [{\n\t\t\"number\": \"84996806958\"\n\t}],\n\t\"addresses\": [{\n\t\t\"street\": \"Rua Feliciano Dias\"\n\t}],\n\t\"linkedin\": \"https://www.linkedin.com/in/jefferson-hsg/\",\n\t\"git\": \"https://github.com/dev-jefferson\"\n}"},"created":1583260251890,"description":"","headers":[{"id":"pair_860a066008ac423083bed5a2b303fbd6","name":"Content-Type","value":"application/json"},{"description":"","id":"pair_e93eb93e86b84e1f9226e9ec229316de","name":"Accept","value":"application/json"}],"isPrivate":false,"metaSortKey":-1583258064421,"method":"POST","modified":1583365668934,"name":"create","parameters":[],"parentId":"fld_7fc51db2559e468297d5ec8b9093e434","settingDisableRenderRequestBody":false,"settingEncodeUrl":true,"settingFollowRedirects":"global","settingRebuildPath":true,"settingSendCookies":true,"settingStoreCookies":true,"url":"{{ app_url  }}/admin/users","_type":"request"},{"_id":"req_0601042d2c8d423db0ba286d06a9d920","authentication":{"token":"{{ token  }}","type":"bearer"},"body":{"mimeType":"application/json","text":"{\n\t\"name\": \"user\",\n\t\"email\": \"jhsg.dev@gmail.com\",\n\t\"username\": \"jhsg20fsf12\",\n\t\"password\": \"12345678\",\n\t\"password_confirmation\": \"12345678\",\n\t\"contacts\": [{\n\t\t\"number\": \"849968068\"\n\t}],\n\t\"addresses\": [{\n\t\t\"street\": \"Rua Feliciano Dias\"\n\t}],\n\t\"linkedin\": \"https://www.linkedin.com/in/jefferson-hsg/\",\n\t\"git\": \"https://github.com/dev-jefferson\"\n}"},"created":1583361933191,"description":"","headers":[{"id":"pair_860a066008ac423083bed5a2b303fbd6","name":"Content-Type","value":"application/json"},{"description":"","id":"pair_e93eb93e86b84e1f9226e9ec229316de","name":"Accept","value":"application/json"}],"isPrivate":false,"metaSortKey":-1581422193239.5,"method":"PUT","modified":1583366362079,"name":"update","parameters":[],"parentId":"fld_7fc51db2559e468297d5ec8b9093e434","settingDisableRenderRequestBody":false,"settingEncodeUrl":true,"settingFollowRedirects":"global","settingRebuildPath":true,"settingSendCookies":true,"settingStoreCookies":true,"url":"{{ app_url  }}/admin/users/5","_type":"request"},{"_id":"req_6e872275d5d54f94b5e124b6b2d91915","authentication":{"disabled":false,"token":"{{ token  }}","type":"bearer"},"body":{},"created":1583363483273,"description":"","headers":[{"description":"","disabled":false,"id":"pair_4b043b7dd8ba4b04933eb16c81732805","name":"Accept","value":"application/json"}],"isPrivate":false,"metaSortKey":-1583258064446,"method":"GET","modified":1583364171516,"name":"get","parameters":[],"parentId":"fld_7fc51db2559e468297d5ec8b9093e434","settingDisableRenderRequestBody":false,"settingEncodeUrl":true,"settingFollowRedirects":"global","settingRebuildPath":true,"settingSendCookies":true,"settingStoreCookies":true,"url":"http://devJob/api/admin/users/4","_type":"request"},{"_id":"req_ed35d920991446ab8235702095201c11","authentication":{"disabled":false,"token":"{{ token  }}","type":"bearer"},"body":{},"created":1583363607314,"description":"","headers":[{"description":"","disabled":false,"id":"pair_4b043b7dd8ba4b04933eb16c81732805","name":"Accept","value":"application/json"}],"isPrivate":false,"metaSortKey":-1581422193189.5,"method":"DELETE","modified":1583364201248,"name":"destroy","parameters":[],"parentId":"fld_7fc51db2559e468297d5ec8b9093e434","settingDisableRenderRequestBody":false,"settingEncodeUrl":true,"settingFollowRedirects":"global","settingRebuildPath":true,"settingSendCookies":true,"settingStoreCookies":true,"url":"http://devJob/api/admin/users/4","_type":"request"},{"_id":"req_b388de06add945f4a0634e893564e3c1","authentication":{"disabled":false,"token":"{{ token  }}","type":"bearer"},"body":{"mimeType":"application/json","text":"{\n\t\"card\": {\n\t\t\"card_expiration_date\": \"1221\", \n\t\t\"card_number\": \"4556148179374159\",\n\t\t\"card_cvv\": \"962\", \n\t\t\"card_holder_name\": \"Jefferson Teste\"\t\n\t},\n\t\"save_card\": false\t\n}\n"},"created":1578179888033,"description":"","headers":[{"id":"pair_fb6e6ba7ccb3417ba41e21f6999736df","name":"Content-Type","value":"application/json"},{"id":"pair_3e4a304dad0b4a6e9888f2429f6b421f","name":"Accept","value":"application/json"}],"isPrivate":false,"metaSortKey":-1572616900376.125,"method":"POST","modified":1579686689082,"name":"Create","parameters":[],"parentId":"fld_73a3ccfbd44b4cd0888d540f9da40b8d","settingDisableRenderRequestBody":false,"settingEncodeUrl":true,"settingFollowRedirects":"global","settingRebuildPath":true,"settingSendCookies":true,"settingStoreCookies":true,"url":"{{ app_url  }}/admin/cards","_type":"request"},{"_id":"fld_73a3ccfbd44b4cd0888d540f9da40b8d","created":1578188184294,"description":"","environment":{},"environmentPropertyOrder":null,"metaSortKey":-1578188184294,"modified":1578188184294,"name":"card","parentId":"fld_0233538b0f594032a3c8460735e23e5b","_type":"request_group"},{"_id":"req_2dec2cc82344437684bb470b142cef28","authentication":{"disabled":false,"token":"{{ token  }}","type":"bearer"},"body":{},"created":1578226905750,"description":"","headers":[{"id":"pair_c8c3e6eaf782426eb842ca2b3a5ac373","name":"Accept","value":"application/json"}],"isPrivate":false,"metaSortKey":-1572616900426.125,"method":"GET","modified":1578226951012,"name":"Index","parameters":[],"parentId":"fld_73a3ccfbd44b4cd0888d540f9da40b8d","settingDisableRenderRequestBody":false,"settingEncodeUrl":true,"settingFollowRedirects":"global","settingRebuildPath":true,"settingSendCookies":true,"settingStoreCookies":true,"url":"{{ app_url  }}/admin/cards","_type":"request"},{"_id":"env_98c729e76b2ff732c19765557a5d58687e799ec5","color":null,"created":1571512035517,"data":{},"dataPropertyOrder":null,"isPrivate":false,"metaSortKey":1571512035517,"modified":1571512035517,"name":"Base Environment","parentId":"wrk_b5a46974959744f4b42af052d1826915","_type":"environment"},{"_id":"jar_98c729e76b2ff732c19765557a5d58687e799ec5","cookies":[{"creation":"2019-10-27T18:39:55.501Z","domain":"api.acordeon.mus.br","hostOnly":true,"httpOnly":true,"id":"6518561064647357","key":"adonis-session","lastAccessed":"2019-10-27T18:39:55.501Z","path":"/","value":"6c6847b1b081abdd044dc3d63b440bae9Nbi0fzzpU83a%2Bnql%2Bw2ezewxvIhZGdslfnRreByg2T8Q8I3H9FEqXLQ9yCC%2BtZkiKBHWIToVaP62GIpCYbcpMr0e9v0KqVITLyIBLT4Qsc4UGaQGhfvJay5LehX%2BNYn"},{"creation":"2019-10-27T18:39:55.502Z","domain":"api.acordeon.mus.br","extensions":["SameSite=Strict"],"hostOnly":true,"id":"7808903301316199","key":"XSRF-TOKEN","lastAccessed":"2019-10-27T18:39:55.502Z","maxAge":7200,"path":"/","value":"9a461518a6661e0cda74bff69208a235wEiuMBy0AowlLn0GTqsxx0vReeIVIp9Su39lC3cnU2Ms62qOfVJidL6tO2r8JDcGCGi70BvdGrKD1JZVVfYwAdICghVAZ3uXSKreiFMJdluM1F%2FaSlvh%2BEAmAi862a7c"},{"creation":"2019-10-27T18:39:55.502Z","domain":"api.acordeon.mus.br","hostOnly":true,"httpOnly":true,"id":"6397308698926663","key":"adonis-session-values","lastAccessed":"2019-10-27T18:39:55.502Z","path":"/","value":"53f5ee175841821118c0929238a6afa6piuFMdo2rlQ%2BagguIpXB%2F%2BtO%2FzPItpt9W9BQlvxepI4anMIAcpadz8CwPVtfL9UdDLquqt6z%2BTrIKFZcOFW%2FUJO1YgYBbVgrfa8SCN%2FAObEtNKIs26HHsSlV0gPTbUoiKFaVtre2ZrdsSlYgrDf6oFx%2B%2FC2NXNBjHUlCKdNy2H0%3D"}],"created":1571512035520,"modified":1572201595503,"name":"Default Jar","parentId":"wrk_b5a46974959744f4b42af052d1826915","_type":"cookie_jar"},{"_id":"env_4ab09530f99fbea2977c0a87d92432d3e0f8781e","color":null,"created":1572418652530,"data":{},"dataPropertyOrder":null,"isPrivate":false,"metaSortKey":1572418652531,"modified":1572418652530,"name":"Base Environment","parentId":"wrk_08b43477c6db4af082f49c7862c41415","_type":"environment"},{"_id":"jar_4ab09530f99fbea2977c0a87d92432d3e0f8781e","cookies":[],"created":1572418652540,"modified":1572418652540,"name":"Default Jar","parentId":"wrk_08b43477c6db4af082f49c7862c41415","_type":"cookie_jar"},{"_id":"env_cb03a5070f5c4a50a5f38d1f699c962f","color":null,"created":1574083815217,"data":{"app_url":"http://acordeon.mus.br:3333/api/v1","app_url_debug":"http://acordeon.mus.br:9229/api/v1","card_hash":"2246284_ZkCCbFbNT3hnazAVrUTKeCc40SpoAY9zKcgL3yR8oYCSUVVKgt9L78mtVChzyfsJCkye7Dn3KqdborYo27wDS+ep8N/mDkZQhdayt5dNy2/vEca/AiSaeQngiVeigHK6ZhVWcZXpCzD4Mwv/3CZtpXuz8+ovfxRyw3NnbfjZE4r6lOsR16uzeuEjTOGcuGzPymzcCQD/5OkqguIZmY7U0XBb114b1wGko8V7xWptzRyzTla2Is4EDDolzCnYyC8T/GAIn5SRtoQdkkknhEv1N34kPs/HVRyOEhKq5K8yUVkOBsaBHnm3bCkx8Ww+LGTm2VC4nz2yUQSB4hfxtfzmIg==","refreshToken":"7c9e5d953068b30b380c2bca6c608dffMBWIjQQtEpbhbMXSg6uWlVeVD7e4qgR4tzGWnIBvd2we1IpHh3aAt9YaEO4N7FUG","token":"eyJhbGciOiJIUzI1NiIsInR5cCI6IkpXVCJ9.eyJ1aWQiOjEsImlhdCI6MTU3OTY5MjgyNH0.0ujDHAmReGd8IsFwb0MQAeXKCF9kgNx2wLjkms0uC0w"},"dataPropertyOrder":{"&":["app_url","app_url_debug","card_hash","token","refreshToken"]},"isPrivate":false,"metaSortKey":1574083815217,"modified":1579698535701,"name":"New Environment","parentId":"env_4ab09530f99fbea2977c0a87d92432d3e0f8781e","_type":"environment"},{"_id":"env_fb7ba4051907153e6e939c81cc8671379ca6af78","color":null,"created":1583255128999,"data":{"app_url":"http://devJob/api","refreshToken":"","token":"eyJ0eXAiOiJKV1QiLCJhbGciOiJIUzI1NiJ9.eyJpc3MiOiJodHRwOlwvXC9kZXZqb2JcL2FwaVwvYXV0aFwvbG9naW4iLCJpYXQiOjE1ODMzNjQzNTcsImV4cCI6MTU4MzM2Nzk1NywibmJmIjoxNTgzMzY0MzU3LCJqdGkiOiJNaXFPR25GNVVWVDJMS25DIiwic3ViIjoxLCJwcnYiOiIxYjJiNzMxNDcxYTIwNGU0ZGFmNTE0Y2JiZWMzY2Y4YTc5ODhlNGIzIn0._NDUXRD1kFhPTW3_PVCJRbW1QHB3r_cfW7smkUmtxUc"},"dataPropertyOrder":{"&":["app_url","token","refreshToken"]},"isPrivate":false,"metaSortKey":1583255128999,"modified":1583364377625,"name":"Base Environment","parentId":"wrk_143fe6bb95d54ed6a82be26e1b978b69","_type":"environment"},{"_id":"jar_fb7ba4051907153e6e939c81cc8671379ca6af78","cookies":[],"created":1583255129005,"modified":1583255129005,"name":"Default Jar","parentId":"wrk_143fe6bb95d54ed6a82be26e1b978b69","_type":"cookie_jar"},{"_id":"env_ec0cf85b9f332fe51492c2f3bff69d3f60796841","color":null,"created":1579586198875,"data":{"app_url":"http://supercorretor.com.br:3333/api/v1","refreshToken":"e80a9333c29df1b6a7a20dfcdc640140CH5LWcUMhV3mN9Ea9A2zUV4StxOvGCLgNMIf/qYGzDvj2P9rFmObOBbvEOveTrkV","token":"eyJhbGciOiJIUzI1NiIsInR5cCI6IkpXVCJ9.eyJ1aWQiOjEsImlhdCI6MTU3OTU4NjkwN30.ko7i7Z-Sc3KUAQZSURC0mlLg8VVzjF6LYbRwHluIrFY"},"dataPropertyOrder":{"&":["app_url","token","refreshToken"]},"isPrivate":false,"metaSortKey":1579586198875,"modified":1579587129117,"name":"Base Environment","parentId":"wrk_25ad120a03044a1d90d4a21232852391","_type":"environment"},{"_id":"jar_ec0cf85b9f332fe51492c2f3bff69d3f60796841","cookies":[],"created":1579586198878,"modified":1579586198878,"name":"Default Jar","parentId":"wrk_25ad120a03044a1d90d4a21232852391","_type":"cookie_jar"}]}